contigion_metatrader/__init__.py
contigion_metatrader/account.py
contigion_metatrader/actions.py
contigion_metatrader/connect.py
contigion_metatrader/data.py
contigion_metatrader/history.py
contigion_metatrader/mappers.py
contigion_metatrader/symbol.py
contigion_metatrader/trades.py
contigion_metatrader/util/__init__.py
contigion_metatrader/util/config.py
contigion_metatrader/util/requests.py
contigion_metatrader-1.0.5.dist-info/METADATA
contigion_metatrader-1.0.5.dist-info/WHEEL
contigion_metatrader-1.0.5.dist-info/top_level.txt
contigion_metatrader-1.0.5.dist-info/RECORD
