Metadata-Version: 2.1
Name: contigion-metatrader
Version: 1.0.5
Summary: A library for retrieving forex data in the Contigion projects
Author-email: Contigion <contigion@gmail.com>
Classifier: Programming Language :: Python :: 3.12
Classifier: Operating System :: OS Independent
Requires-Dist: pandas
Requires-Dist: MetaTrader5
Requires-Dist: contigion_utils
Requires-Dist: datetime
